insiderTrades/__init__.py
insiderTrades/derivativeHoldingsPullAndScrape.py
insiderTrades/derivativeHoldingsScrape.py
insiderTrades/derivativeTransactionsPullAndScrape.py
insiderTrades/derivativeTransactionsScrape.py
insiderTrades/nonderivativeHoldingsPullAndScrape.py
insiderTrades/nonderivativeHoldingsScrape.py
insiderTrades/nonderivativeTransactionsPullAndScrape.py
insiderTrades/nonderivativeTransactionsScrape.py
insiderTrades/secUrlDownload.py
insiderTrades/utils/__init__.py
insiderTrades/utils/footnoteScrape.py
insiderTrades/utils/formFilterDerivativeHoldings.py
insiderTrades/utils/formFilterDerivativeTransactions.py
insiderTrades/utils/formFilterNonderivativeHoldings.py
insiderTrades/utils/formFilterNonderivativeTransactions.py
insiderTrades/utils/transactionFilterDerivative.py
insiderTrades/utils/transactionFilterDerivativeHoldings.py
insiderTrades/utils/transactionFilterNonderivative.py
insiderTrades/utils/transactionFilterNonderivativeHoldings.py
insiderTrades/utils/transactionScrape.py
insiderTrades-1.0.0.dist-info/LICENSE.txt
insiderTrades-1.0.0.dist-info/METADATA
insiderTrades-1.0.0.dist-info/WHEEL
insiderTrades-1.0.0.dist-info/top_level.txt
insiderTrades-1.0.0.dist-info/RECORD
